fossbill/__init__.py
fossbill/alembic.ini
fossbill/auth.py
fossbill/bill.py
fossbill/customer.py
fossbill/database.py
fossbill/fake.py
fossbill/landing.py
fossbill/me.py
fossbill/payment.py
fossbill/product.py
fossbill/user.py
fossbill/alembic/env.py
fossbill/alembic/script.py.mako
fossbill/alembic/versions/21487ff4ab8c_store_receipt_url_in_payment.py
fossbill/alembic/versions/531dff33369c_add_logo_url.py
fossbill/alembic/versions/7899e98936b3_bills_date_to_created_at.py
fossbill/alembic/versions/8b4e2235b960_add_bill_style.py
fossbill/alembic/versions/ac14f3a73a29_rename_client_to_customer.py
fossbill/alembic/versions/e73b0c0cdf0b_add_user_free.py
fossbill/alembic/versions/fd9bee91aa0f_.py
fossbill/alembic/versions/fda694e67f67_init.py
fossbill/alembic/versions/ff51555aa2ba_add_date_on_bills_and_quotes.py
fossbill/locale/en_US/LC_MESSAGES/messages.mo
fossbill/locale/fr_FR/LC_MESSAGES/messages.mo
fossbill/static/bill.css
fossbill/static/style.css
fossbill/templates/base.html
fossbill/templates/macros.html
fossbill/templates/auth/ask_reset_password.html
fossbill/templates/auth/login.html
fossbill/templates/auth/register.html
fossbill/templates/auth/reset_password_email.plain
fossbill/templates/auth/use_reset_password.html
fossbill/templates/bill/bill_email.plain
fossbill/templates/bill/create.html
fossbill/templates/bill/create_row.html
fossbill/templates/bill/finish.html
fossbill/templates/bill/generated_bill.html
fossbill/templates/bill/generated_draft.html
fossbill/templates/bill/generated_quote.html
fossbill/templates/bill/index.html
fossbill/templates/bill/quote_email.plain
fossbill/templates/bill/send_bill_email.html
fossbill/templates/bill/send_quote_email.html
fossbill/templates/bill/update.html
fossbill/templates/bill/update_bill.html
fossbill/templates/bill/update_quote.html
fossbill/templates/bill/update_row.html
fossbill/templates/customer/create.html
fossbill/templates/customer/index.html
fossbill/templates/customer/update.html
fossbill-1.9.0.dist-info/METADATA
fossbill-1.9.0.dist-info/WHEEL
fossbill-1.9.0.dist-info/licenses/LICENSE
fossbill-1.9.0.dist-info/RECORD
