Metadata-Version: 2.3
Name: fossbill
Version: 1.9.0
Summary: A simple billing tool
Project-URL: Homepage, https://sr.ht/~stacyharper/fossbill/
Author-email: Willow Barraco <contact@willowbarraco.fr>
License-File: LICENSE
Classifier: License :: OSI Approved :: GNU Affero General Public License v3 or later (AGPLv3+)
Classifier: Operating System :: OS Independent
Classifier: Programming Language :: Python :: 3
Requires-Python: >=3.8
Requires-Dist: alembic
Requires-Dist: babel
Requires-Dist: faker
Requires-Dist: flask-weasyprint
Requires-Dist: sqlalchemy>=2.0.0
Requires-Dist: stripe
Requires-Dist: toml
